{
  "content": [
    {
      "content": null,
      "created": "2025-10-05T22:38:56.934726Z",
      "format": null,
      "hash": null,
      "hash_algorithm": null,
      "last_modified": "2025-10-05T22:29:59.339044Z",
      "mimetype": "video/mp4",
      "name": "soldering_smd.mp4",
      "path": "_static/videos/soldering_smd.mp4",
      "size": 6978131,
      "type": "file",
      "writable": true
    },
    {
      "content": null,
      "created": "2025-10-05T22:38:56.897726Z",
      "format": null,
      "hash": null,
      "hash_algorithm": null,
      "last_modified": "2025-10-05T22:29:59.245045Z",
      "mimetype": "video/mp4",
      "name": "IC_inpackage.mp4",
      "path": "_static/videos/IC_inpackage.mp4",
      "size": 11786330,
      "type": "file",
      "writable": true
    },
    {
      "content": null,
      "created": "2025-10-05T22:38:56.929726Z",
      "format": null,
      "hash": null,
      "hash_algorithm": null,
      "last_modified": "2025-10-05T22:29:59.326044Z",
      "mimetype": "video/mp4",
      "name": "making_of_a_4-layer_pcb.mp4",
      "path": "_static/videos/making_of_a_4-layer_pcb.mp4",
      "size": 49758821,
      "type": "file",
      "writable": true
    },
    {
      "content": null,
      "created": "2025-10-05T22:38:56.897726Z",
      "format": null,
      "hash": null,
      "hash_algorithm": null,
      "last_modified": "2025-10-05T22:29:59.247045Z",
      "mimetype": "text/markdown",
      "name": "bronnen.md",
      "path": "_static/videos/bronnen.md",
      "size": 101,
      "type": "file",
      "writable": true
    }
  ],
  "created": "2025-10-05T22:38:56.930726Z",
  "format": "json",
  "hash": null,
  "hash_algorithm": null,
  "last_modified": "2025-10-05T22:38:56.930726Z",
  "mimetype": null,
  "name": "videos",
  "path": "_static/videos",
  "size": null,
  "type": "directory",
  "writable": true
}