{
  "content": [
    {
      "content": null,
      "created": "2025-10-04T23:43:14.218530Z",
      "format": null,
      "hash": null,
      "hash_algorithm": null,
      "last_modified": "2025-10-04T23:34:00.084430Z",
      "mimetype": "video/mp4",
      "name": "soldering_smd.mp4",
      "path": "_static/videos/soldering_smd.mp4",
      "size": 6978131,
      "type": "file",
      "writable": true
    },
    {
      "content": null,
      "created": "2025-10-04T23:43:14.181530Z",
      "format": null,
      "hash": null,
      "hash_algorithm": null,
      "last_modified": "2025-10-04T23:33:59.986429Z",
      "mimetype": "video/mp4",
      "name": "IC_inpackage.mp4",
      "path": "_static/videos/IC_inpackage.mp4",
      "size": 11786330,
      "type": "file",
      "writable": true
    },
    {
      "content": null,
      "created": "2025-10-04T23:43:14.213530Z",
      "format": null,
      "hash": null,
      "hash_algorithm": null,
      "last_modified": "2025-10-04T23:34:00.071429Z",
      "mimetype": "video/mp4",
      "name": "making_of_a_4-layer_pcb.mp4",
      "path": "_static/videos/making_of_a_4-layer_pcb.mp4",
      "size": 49758821,
      "type": "file",
      "writable": true
    },
    {
      "content": null,
      "created": "2025-10-04T23:43:14.182530Z",
      "format": null,
      "hash": null,
      "hash_algorithm": null,
      "last_modified": "2025-10-04T23:33:59.988429Z",
      "mimetype": "text/markdown",
      "name": "bronnen.md",
      "path": "_static/videos/bronnen.md",
      "size": 101,
      "type": "file",
      "writable": true
    }
  ],
  "created": "2025-10-04T23:43:14.213530Z",
  "format": "json",
  "hash": null,
  "hash_algorithm": null,
  "last_modified": "2025-10-04T23:43:14.213530Z",
  "mimetype": null,
  "name": "videos",
  "path": "_static/videos",
  "size": null,
  "type": "directory",
  "writable": true
}