{
  "content": [
    {
      "content": null,
      "created": "2024-01-05T17:08:06.726748Z",
      "format": null,
      "hash": null,
      "hash_algorithm": null,
      "last_modified": "2024-01-05T17:02:50.557694Z",
      "mimetype": null,
      "name": "_toc.yml",
      "path": "_toc.yml",
      "size": 921,
      "type": "file",
      "writable": true
    },
    {
      "content": null,
      "created": "2024-01-05T17:08:06.734748Z",
      "format": null,
      "hash": null,
      "hash_algorithm": null,
      "last_modified": "2024-01-05T17:02:50.565694Z",
      "mimetype": null,
      "name": "reflecties.ipynb",
      "path": "reflecties.ipynb",
      "size": 47717,
      "type": "notebook",
      "writable": true
    },
    {
      "content": null,
      "created": "2024-01-05T17:08:06.670747Z",
      "format": null,
      "hash": null,
      "hash_algorithm": null,
      "last_modified": "2024-01-05T17:02:50.473694Z",
      "mimetype": null,
      "name": "Klasse-D.ipynb",
      "path": "Klasse-D.ipynb",
      "size": 1545808,
      "type": "notebook",
      "writable": true
    },
    {
      "content": null,
      "created": "2024-01-05T17:08:06.706748Z",
      "format": null,
      "hash": null,
      "hash_algorithm": null,
      "last_modified": "2024-01-05T17:02:50.533694Z",
      "mimetype": null,
      "name": "SmithKaartOefening4.ipynb",
      "path": "SmithKaartOefening4.ipynb",
      "size": 2296647,
      "type": "notebook",
      "writable": true
    },
    {
      "content": null,
      "created": "2024-01-05T17:08:06.734748Z",
      "format": null,
      "hash": null,
      "hash_algorithm": null,
      "last_modified": "2024-01-05T17:08:06.734748Z",
      "mimetype": null,
      "name": "images",
      "path": "images",
      "size": null,
      "type": "directory",
      "writable": true
    },
    {
      "content": null,
      "created": "2024-01-05T17:08:06.734748Z",
      "format": null,
      "hash": null,
      "hash_algorithm": null,
      "last_modified": "2024-01-05T17:02:50.565694Z",
      "mimetype": "text/markdown",
      "name": "intro.md",
      "path": "intro.md",
      "size": 963,
      "type": "file",
      "writable": true
    },
    {
      "content": null,
      "created": "2024-01-05T17:08:06.674747Z",
      "format": null,
      "hash": null,
      "hash_algorithm": null,
      "last_modified": "2024-01-05T17:02:50.485694Z",
      "mimetype": null,
      "name": "Klasse-E.ipynb",
      "path": "Klasse-E.ipynb",
      "size": 3040922,
      "type": "notebook",
      "writable": true
    },
    {
      "content": null,
      "created": "2024-01-05T17:08:06.686747Z",
      "format": null,
      "hash": null,
      "hash_algorithm": null,
      "last_modified": "2024-01-05T17:02:50.493694Z",
      "mimetype": null,
      "name": "SmithKaart.ipynb",
      "path": "SmithKaart.ipynb",
      "size": 1487860,
      "type": "notebook",
      "writable": true
    },
    {
      "content": null,
      "created": "2024-01-05T17:08:06.686747Z",
      "format": null,
      "hash": null,
      "hash_algorithm": null,
      "last_modified": "2024-01-05T17:02:50.489694Z",
      "mimetype": "text/markdown",
      "name": "References.md",
      "path": "References.md",
      "size": 53,
      "type": "file",
      "writable": true
    },
    {
      "content": null,
      "created": "2024-01-05T17:08:06.718747Z",
      "format": null,
      "hash": null,
      "hash_algorithm": null,
      "last_modified": "2024-01-05T17:02:50.553694Z",
      "mimetype": null,
      "name": "SmithKaartOefening7.ipynb",
      "path": "SmithKaartOefening7.ipynb",
      "size": 503498,
      "type": "notebook",
      "writable": true
    },
    {
      "content": null,
      "created": "2024-01-05T17:08:06.722748Z",
      "format": null,
      "hash": null,
      "hash_algorithm": null,
      "last_modified": "2024-01-05T17:02:50.557694Z",
      "mimetype": null,
      "name": "Spice-simulatie.ipynb",
      "path": "Spice-simulatie.ipynb",
      "size": 412589,
      "type": "notebook",
      "writable": true
    },
    {
      "content": null,
      "created": "2024-01-05T17:08:06.726748Z",
      "format": null,
      "hash": null,
      "hash_algorithm": null,
      "last_modified": "2024-01-05T17:08:05.090743Z",
      "mimetype": "text/x-python",
      "name": "cursusdef.py",
      "path": "cursusdef.py",
      "size": 779,
      "type": "file",
      "writable": true
    },
    {
      "content": null,
      "created": "2024-01-05T17:08:06.718747Z",
      "format": null,
      "hash": null,
      "hash_algorithm": null,
      "last_modified": "2024-01-05T17:02:50.549694Z",
      "mimetype": null,
      "name": "SmithKaartOefening6.ipynb",
      "path": "SmithKaartOefening6.ipynb",
      "size": 661902,
      "type": "notebook",
      "writable": true
    },
    {
      "content": null,
      "created": "2024-01-05T17:08:06.658747Z",
      "format": null,
      "hash": null,
      "hash_algorithm": null,
      "last_modified": "2024-01-05T17:02:50.449694Z",
      "mimetype": null,
      "name": "Filters.ipynb",
      "path": "Filters.ipynb",
      "size": 1336001,
      "type": "notebook",
      "writable": true
    },
    {
      "content": null,
      "created": "2024-01-05T17:08:06.726748Z",
      "format": null,
      "hash": null,
      "hash_algorithm": null,
      "last_modified": "2024-01-05T17:02:50.557694Z",
      "mimetype": null,
      "name": "_config.yml",
      "path": "_config.yml",
      "size": 1903,
      "type": "file",
      "writable": true
    },
    {
      "content": null,
      "created": "2024-01-05T17:08:06.738748Z",
      "format": null,
      "hash": null,
      "hash_algorithm": null,
      "last_modified": "2024-01-05T17:08:06.738748Z",
      "mimetype": null,
      "name": "simul",
      "path": "simul",
      "size": null,
      "type": "directory",
      "writable": true
    },
    {
      "content": null,
      "created": "2024-01-05T17:08:06.662747Z",
      "format": null,
      "hash": null,
      "hash_algorithm": null,
      "last_modified": "2024-01-05T17:02:50.465694Z",
      "mimetype": null,
      "name": "Klasse-C.ipynb",
      "path": "Klasse-C.ipynb",
      "size": 3020629,
      "type": "notebook",
      "writable": true
    },
    {
      "content": null,
      "created": "2024-01-05T17:08:06.738748Z",
      "format": null,
      "hash": null,
      "hash_algorithm": null,
      "last_modified": "2024-01-05T17:02:50.565694Z",
      "mimetype": null,
      "name": "transmissielijn.ipynb",
      "path": "transmissielijn.ipynb",
      "size": 259480,
      "type": "notebook",
      "writable": true
    },
    {
      "content": null,
      "created": "2024-01-05T17:08:06.722748Z",
      "format": null,
      "hash": null,
      "hash_algorithm": null,
      "last_modified": "2024-01-05T17:02:50.557694Z",
      "mimetype": null,
      "name": "SmithKaartOefening8.ipynb",
      "path": "SmithKaartOefening8.ipynb",
      "size": 752584,
      "type": "notebook",
      "writable": true
    },
    {
      "content": null,
      "created": "2024-01-05T17:08:06.726748Z",
      "format": null,
      "hash": null,
      "hash_algorithm": null,
      "last_modified": "2024-01-05T17:02:50.557694Z",
      "mimetype": null,
      "name": "_tocpdf.yml",
      "path": "_tocpdf.yml",
      "size": 654,
      "type": "file",
      "writable": true
    },
    {
      "content": null,
      "created": "2024-01-05T17:08:06.726748Z",
      "format": null,
      "hash": null,
      "hash_algorithm": null,
      "last_modified": "2024-01-05T17:02:50.557694Z",
      "mimetype": "text/x-bibtex",
      "name": "ToegepasteAnalogeElektronica.bib",
      "path": "ToegepasteAnalogeElektronica.bib",
      "size": 6095,
      "type": "file",
      "writable": true
    },
    {
      "content": null,
      "created": "2024-01-05T17:08:06.694747Z",
      "format": null,
      "hash": null,
      "hash_algorithm": null,
      "last_modified": "2024-01-05T17:02:50.509694Z",
      "mimetype": null,
      "name": "SmithKaartOefening2.ipynb",
      "path": "SmithKaartOefening2.ipynb",
      "size": 2271471,
      "type": "notebook",
      "writable": true
    },
    {
      "content": null,
      "created": "2024-01-05T17:08:06.690747Z",
      "format": null,
      "hash": null,
      "hash_algorithm": null,
      "last_modified": "2024-01-05T17:02:50.497694Z",
      "mimetype": null,
      "name": "SmithKaartOefening1.ipynb",
      "path": "SmithKaartOefening1.ipynb",
      "size": 802902,
      "type": "notebook",
      "writable": true
    },
    {
      "content": null,
      "created": "2024-01-05T17:08:06.734748Z",
      "format": null,
      "hash": null,
      "hash_algorithm": null,
      "last_modified": "2024-01-05T17:02:50.565694Z",
      "mimetype": "text/markdown",
      "name": "intro2.md",
      "path": "intro2.md",
      "size": 569,
      "type": "file",
      "writable": true
    },
    {
      "content": null,
      "created": "2024-01-05T17:08:06.698747Z",
      "format": null,
      "hash": null,
      "hash_algorithm": null,
      "last_modified": "2024-01-05T17:02:50.521694Z",
      "mimetype": null,
      "name": "SmithKaartOefening3.ipynb",
      "path": "SmithKaartOefening3.ipynb",
      "size": 2273194,
      "type": "notebook",
      "writable": true
    },
    {
      "content": null,
      "created": "2024-01-05T17:08:06.714747Z",
      "format": null,
      "hash": null,
      "hash_algorithm": null,
      "last_modified": "2024-01-05T17:02:50.545694Z",
      "mimetype": null,
      "name": "SmithKaartOefening5.ipynb",
      "path": "SmithKaartOefening5.ipynb",
      "size": 2349348,
      "type": "notebook",
      "writable": true
    },
    {
      "content": null,
      "created": "2024-01-05T17:08:06.682747Z",
      "format": null,
      "hash": null,
      "hash_algorithm": null,
      "last_modified": "2024-01-05T17:02:50.489694Z",
      "mimetype": null,
      "name": "Klasse-F.ipynb",
      "path": "Klasse-F.ipynb",
      "size": 848198,
      "type": "notebook",
      "writable": true
    }
  ],
  "created": "2024-01-05T17:08:06.738748Z",
  "format": "json",
  "hash": null,
  "hash_algorithm": null,
  "last_modified": "2024-01-05T17:08:06.738748Z",
  "mimetype": null,
  "name": "",
  "path": "",
  "size": null,
  "type": "directory",
  "writable": true
}