{
  "content": [
    {
      "content": null,
      "created": "2022-12-10T23:00:23.183583Z",
      "format": null,
      "last_modified": "2022-12-10T23:00:21.011597Z",
      "mimetype": null,
      "name": "SmithKaartOefening2.ipynb",
      "path": "SmithKaartOefening2.ipynb",
      "size": 2269726,
      "type": "notebook",
      "writable": true
    },
    {
      "content": null,
      "created": "2022-12-10T23:00:23.223583Z",
      "format": null,
      "last_modified": "2022-12-10T23:00:23.223583Z",
      "mimetype": null,
      "name": "simul",
      "path": "simul",
      "size": null,
      "type": "directory",
      "writable": true
    },
    {
      "content": null,
      "created": "2022-12-10T23:00:23.167583Z",
      "format": null,
      "last_modified": "2022-12-10T23:00:21.071596Z",
      "mimetype": null,
      "name": "Klasse-D.ipynb",
      "path": "Klasse-D.ipynb",
      "size": 1336505,
      "type": "notebook",
      "writable": true
    },
    {
      "content": null,
      "created": "2022-12-10T23:00:23.191583Z",
      "format": null,
      "last_modified": "2022-12-10T23:00:21.123596Z",
      "mimetype": null,
      "name": "SmithKaartOefening3.ipynb",
      "path": "SmithKaartOefening3.ipynb",
      "size": 2276396,
      "type": "notebook",
      "writable": true
    },
    {
      "content": null,
      "created": "2022-12-10T23:00:23.215583Z",
      "format": null,
      "last_modified": "2022-12-10T23:00:00.379745Z",
      "mimetype": "text/x-python",
      "name": "cursusdef.py",
      "path": "cursusdef.py",
      "size": 779,
      "type": "file",
      "writable": true
    },
    {
      "content": null,
      "created": "2022-12-10T23:00:23.219583Z",
      "format": null,
      "last_modified": "2022-12-10T23:00:23.219583Z",
      "mimetype": null,
      "name": "images",
      "path": "images",
      "size": null,
      "type": "directory",
      "writable": true
    },
    {
      "content": null,
      "created": "2022-12-10T23:00:23.159583Z",
      "format": null,
      "last_modified": "2022-12-10T23:00:21.239595Z",
      "mimetype": null,
      "name": "Klasse-C.ipynb",
      "path": "Klasse-C.ipynb",
      "size": 2616043,
      "type": "notebook",
      "writable": true
    },
    {
      "content": null,
      "created": "2022-12-10T23:00:23.179583Z",
      "format": null,
      "last_modified": "2022-12-10T23:00:21.259595Z",
      "mimetype": null,
      "name": "Klasse-F.ipynb",
      "path": "Klasse-F.ipynb",
      "size": 835808,
      "type": "notebook",
      "writable": true
    },
    {
      "content": null,
      "created": "2022-12-10T23:00:23.219583Z",
      "format": null,
      "last_modified": "2022-12-10T23:00:21.267595Z",
      "mimetype": null,
      "name": "reflecties.ipynb",
      "path": "reflecties.ipynb",
      "size": 51614,
      "type": "notebook",
      "writable": true
    },
    {
      "content": null,
      "created": "2022-12-10T23:00:23.199583Z",
      "format": null,
      "last_modified": "2022-12-10T23:00:21.315595Z",
      "mimetype": null,
      "name": "SmithKaartOefening4.ipynb",
      "path": "SmithKaartOefening4.ipynb",
      "size": 2299697,
      "type": "notebook",
      "writable": true
    },
    {
      "content": null,
      "created": "2022-12-10T23:00:23.155583Z",
      "format": null,
      "last_modified": "2022-12-10T23:00:21.371594Z",
      "mimetype": null,
      "name": "Filters.ipynb",
      "path": "Filters.ipynb",
      "size": 1292500,
      "type": "notebook",
      "writable": true
    },
    {
      "content": null,
      "created": "2022-12-10T23:00:23.215583Z",
      "format": null,
      "last_modified": "2022-12-10T22:59:13.720004Z",
      "mimetype": null,
      "name": "_config.yml",
      "path": "_config.yml",
      "size": 1368,
      "type": "file",
      "writable": true
    },
    {
      "content": null,
      "created": "2022-12-10T23:00:23.183583Z",
      "format": null,
      "last_modified": "2022-12-10T23:00:21.383595Z",
      "mimetype": null,
      "name": "SmithKaartOefening1.ipynb",
      "path": "SmithKaartOefening1.ipynb",
      "size": 233976,
      "type": "notebook",
      "writable": true
    },
    {
      "content": null,
      "created": "2022-12-10T23:00:23.203583Z",
      "format": null,
      "last_modified": "2022-12-10T23:00:21.435594Z",
      "mimetype": null,
      "name": "SmithKaartOefening5.ipynb",
      "path": "SmithKaartOefening5.ipynb",
      "size": 2292967,
      "type": "notebook",
      "writable": true
    },
    {
      "content": null,
      "created": "2022-12-10T23:00:23.179583Z",
      "format": null,
      "last_modified": "2022-12-10T23:00:21.435594Z",
      "mimetype": null,
      "name": "SmithKaart.ipynb",
      "path": "SmithKaart.ipynb",
      "size": 5322,
      "type": "notebook",
      "writable": true
    },
    {
      "content": null,
      "created": "2022-12-10T23:00:23.171583Z",
      "format": null,
      "last_modified": "2022-12-10T23:00:21.503594Z",
      "mimetype": null,
      "name": "Klasse-E.ipynb",
      "path": "Klasse-E.ipynb",
      "size": 2774733,
      "type": "notebook",
      "writable": true
    },
    {
      "content": null,
      "created": "2022-12-10T23:00:23.227582Z",
      "format": null,
      "last_modified": "2022-12-10T23:00:21.519593Z",
      "mimetype": null,
      "name": "transmissielijn.ipynb",
      "path": "transmissielijn.ipynb",
      "size": 259906,
      "type": "notebook",
      "writable": true
    },
    {
      "content": null,
      "created": "2022-12-10T23:00:23.211583Z",
      "format": null,
      "last_modified": "2022-12-10T23:00:21.535594Z",
      "mimetype": null,
      "name": "SmithKaartOefening7.ipynb",
      "path": "SmithKaartOefening7.ipynb",
      "size": 496108,
      "type": "notebook",
      "writable": true
    },
    {
      "content": null,
      "created": "2022-12-10T23:00:23.215583Z",
      "format": null,
      "last_modified": "2022-12-10T22:59:13.720004Z",
      "mimetype": null,
      "name": "_toc.yml",
      "path": "_toc.yml",
      "size": 671,
      "type": "file",
      "writable": true
    },
    {
      "content": null,
      "created": "2022-12-10T23:00:23.215583Z",
      "format": null,
      "last_modified": "2022-12-10T23:00:21.555593Z",
      "mimetype": null,
      "name": "Spice-simulatie.ipynb",
      "path": "Spice-simulatie.ipynb",
      "size": 408737,
      "type": "notebook",
      "writable": true
    },
    {
      "content": null,
      "created": "2022-12-10T23:00:23.211583Z",
      "format": null,
      "last_modified": "2022-12-10T23:00:21.571593Z",
      "mimetype": null,
      "name": "SmithKaartOefening6.ipynb",
      "path": "SmithKaartOefening6.ipynb",
      "size": 666059,
      "type": "notebook",
      "writable": true
    },
    {
      "content": null,
      "created": "2022-12-10T23:00:23.219583Z",
      "format": null,
      "last_modified": "2022-12-10T22:59:13.720004Z",
      "mimetype": "text/markdown",
      "name": "intro.md",
      "path": "intro.md",
      "size": 1228,
      "type": "file",
      "writable": true
    }
  ],
  "created": "2022-12-10T23:00:23.223583Z",
  "format": "json",
  "last_modified": "2022-12-10T23:00:23.223583Z",
  "mimetype": null,
  "name": "",
  "path": "",
  "size": null,
  "type": "directory",
  "writable": true
}