{
  "content": [
    {
      "content": null,
      "created": "2025-11-17T23:57:04.547901Z",
      "format": null,
      "hash": null,
      "hash_algorithm": null,
      "last_modified": "2025-11-17T23:57:00.899876Z",
      "mimetype": null,
      "name": "Klasse-C.ipynb",
      "path": "Klasse-C.ipynb",
      "size": 3072744,
      "type": "notebook",
      "writable": true
    },
    {
      "content": null,
      "created": "2025-11-17T23:57:04.614901Z",
      "format": null,
      "hash": null,
      "hash_algorithm": null,
      "last_modified": "2025-11-17T23:51:01.845313Z",
      "mimetype": "application/yaml",
      "name": "_tocpdf.yml",
      "path": "_tocpdf.yml",
      "size": 735,
      "type": "file",
      "writable": true
    },
    {
      "content": null,
      "created": "2025-11-17T23:57:04.581901Z",
      "format": null,
      "hash": null,
      "hash_algorithm": null,
      "last_modified": "2025-11-17T23:57:00.937876Z",
      "mimetype": null,
      "name": "SmithKaartOefening2.ipynb",
      "path": "SmithKaartOefening2.ipynb",
      "size": 2336229,
      "type": "notebook",
      "writable": true
    },
    {
      "content": null,
      "created": "2025-11-17T23:57:04.612901Z",
      "format": null,
      "hash": null,
      "hash_algorithm": null,
      "last_modified": "2025-11-17T23:57:00.951876Z",
      "mimetype": null,
      "name": "Spice-simulatie.ipynb",
      "path": "Spice-simulatie.ipynb",
      "size": 421872,
      "type": "notebook",
      "writable": true
    },
    {
      "content": null,
      "created": "2025-11-17T23:57:04.614901Z",
      "format": null,
      "hash": null,
      "hash_algorithm": null,
      "last_modified": "2025-11-17T23:56:46.470777Z",
      "mimetype": "text/x-python",
      "name": "cursusdef.py",
      "path": "cursusdef.py",
      "size": 779,
      "type": "file",
      "writable": true
    },
    {
      "content": null,
      "created": "2025-11-17T23:57:04.601901Z",
      "format": null,
      "hash": null,
      "hash_algorithm": null,
      "last_modified": "2025-11-17T23:57:00.988876Z",
      "mimetype": null,
      "name": "SmithKaartOefening5.ipynb",
      "path": "SmithKaartOefening5.ipynb",
      "size": 2358585,
      "type": "notebook",
      "writable": true
    },
    {
      "content": null,
      "created": "2025-11-17T23:57:04.627901Z",
      "format": null,
      "hash": null,
      "hash_algorithm": null,
      "last_modified": "2025-11-17T23:57:01.017877Z",
      "mimetype": null,
      "name": "reflecties.ipynb",
      "path": "reflecties.ipynb",
      "size": 53538,
      "type": "notebook",
      "writable": true
    },
    {
      "content": null,
      "created": "2025-11-17T23:57:04.567901Z",
      "format": null,
      "hash": null,
      "hash_algorithm": null,
      "last_modified": "2025-11-17T23:57:01.079877Z",
      "mimetype": null,
      "name": "Klasse-F.ipynb",
      "path": "Klasse-F.ipynb",
      "size": 1375942,
      "type": "notebook",
      "writable": true
    },
    {
      "content": null,
      "created": "2025-11-17T23:57:04.569901Z",
      "format": null,
      "hash": null,
      "hash_algorithm": null,
      "last_modified": "2025-11-17T23:51:01.768312Z",
      "mimetype": "text/markdown",
      "name": "References.md",
      "path": "References.md",
      "size": 53,
      "type": "file",
      "writable": true
    },
    {
      "content": null,
      "created": "2025-11-17T23:57:04.626901Z",
      "format": null,
      "hash": null,
      "hash_algorithm": null,
      "last_modified": "2025-11-17T23:57:04.626901Z",
      "mimetype": null,
      "name": "images",
      "path": "images",
      "size": null,
      "type": "directory",
      "writable": true
    },
    {
      "content": null,
      "created": "2025-11-17T23:57:04.587901Z",
      "format": null,
      "hash": null,
      "hash_algorithm": null,
      "last_modified": "2025-11-17T23:57:01.116877Z",
      "mimetype": null,
      "name": "SmithKaartOefening3.ipynb",
      "path": "SmithKaartOefening3.ipynb",
      "size": 2350592,
      "type": "notebook",
      "writable": true
    },
    {
      "content": null,
      "created": "2025-11-17T23:57:04.613901Z",
      "format": null,
      "hash": null,
      "hash_algorithm": null,
      "last_modified": "2025-11-17T23:51:01.845313Z",
      "mimetype": "text/x-bibtex",
      "name": "ToegepasteAnalogeElektronica.bib",
      "path": "ToegepasteAnalogeElektronica.bib",
      "size": 17285,
      "type": "file",
      "writable": true
    },
    {
      "content": null,
      "created": "2025-11-17T23:57:04.554901Z",
      "format": null,
      "hash": null,
      "hash_algorithm": null,
      "last_modified": "2025-11-17T23:57:01.152878Z",
      "mimetype": null,
      "name": "Klasse-D.ipynb",
      "path": "Klasse-D.ipynb",
      "size": 1566085,
      "type": "notebook",
      "writable": true
    },
    {
      "content": null,
      "created": "2025-11-17T23:57:04.633901Z",
      "format": null,
      "hash": null,
      "hash_algorithm": null,
      "last_modified": "2025-11-17T23:57:01.168878Z",
      "mimetype": null,
      "name": "transmissielijn.ipynb",
      "path": "transmissielijn.ipynb",
      "size": 350931,
      "type": "notebook",
      "writable": true
    },
    {
      "content": null,
      "created": "2025-11-17T23:57:04.614901Z",
      "format": null,
      "hash": null,
      "hash_algorithm": null,
      "last_modified": "2025-11-17T23:57:04.614901Z",
      "mimetype": null,
      "name": "extra_path",
      "path": "extra_path",
      "size": null,
      "type": "directory",
      "writable": true
    },
    {
      "content": null,
      "created": "2025-11-17T23:57:04.610901Z",
      "format": null,
      "hash": null,
      "hash_algorithm": null,
      "last_modified": "2025-11-17T23:57:01.182878Z",
      "mimetype": null,
      "name": "SmithKaartOefening8.ipynb",
      "path": "SmithKaartOefening8.ipynb",
      "size": 755277,
      "type": "notebook",
      "writable": true
    },
    {
      "content": null,
      "created": "2025-11-17T23:57:04.571901Z",
      "format": null,
      "hash": null,
      "hash_algorithm": null,
      "last_modified": "2025-11-17T23:57:01.197878Z",
      "mimetype": null,
      "name": "SmithKaart.ipynb",
      "path": "SmithKaart.ipynb",
      "size": 1696224,
      "type": "notebook",
      "writable": true
    },
    {
      "content": null,
      "created": "2025-11-17T23:57:04.608901Z",
      "format": null,
      "hash": null,
      "hash_algorithm": null,
      "last_modified": "2025-11-17T23:57:01.213878Z",
      "mimetype": null,
      "name": "SmithKaartOefening7.ipynb",
      "path": "SmithKaartOefening7.ipynb",
      "size": 976003,
      "type": "notebook",
      "writable": true
    },
    {
      "content": null,
      "created": "2025-11-17T23:57:04.613901Z",
      "format": null,
      "hash": null,
      "hash_algorithm": null,
      "last_modified": "2025-11-17T23:51:01.845313Z",
      "mimetype": "application/yaml",
      "name": "_config.yml",
      "path": "_config.yml",
      "size": 2129,
      "type": "file",
      "writable": true
    },
    {
      "content": null,
      "created": "2025-11-17T23:57:04.594901Z",
      "format": null,
      "hash": null,
      "hash_algorithm": null,
      "last_modified": "2025-11-17T23:57:01.250878Z",
      "mimetype": null,
      "name": "SmithKaartOefening4.ipynb",
      "path": "SmithKaartOefening4.ipynb",
      "size": 2307216,
      "type": "notebook",
      "writable": true
    },
    {
      "content": null,
      "created": "2025-11-17T23:57:04.575901Z",
      "format": null,
      "hash": null,
      "hash_algorithm": null,
      "last_modified": "2025-11-17T23:57:01.276878Z",
      "mimetype": null,
      "name": "SmithKaartOefening1.ipynb",
      "path": "SmithKaartOefening1.ipynb",
      "size": 2314803,
      "type": "notebook",
      "writable": true
    },
    {
      "content": null,
      "created": "2025-11-17T23:57:04.626901Z",
      "format": null,
      "hash": null,
      "hash_algorithm": null,
      "last_modified": "2025-11-17T23:51:01.854313Z",
      "mimetype": "text/markdown",
      "name": "intro.md",
      "path": "intro.md",
      "size": 2668,
      "type": "file",
      "writable": true
    },
    {
      "content": null,
      "created": "2025-11-17T23:57:04.634901Z",
      "format": null,
      "hash": null,
      "hash_algorithm": null,
      "last_modified": "2025-11-17T23:57:04.634901Z",
      "mimetype": null,
      "name": "video",
      "path": "video",
      "size": null,
      "type": "directory",
      "writable": true
    },
    {
      "content": null,
      "created": "2025-11-17T23:57:04.559901Z",
      "format": null,
      "hash": null,
      "hash_algorithm": null,
      "last_modified": "2025-11-17T23:57:01.337879Z",
      "mimetype": null,
      "name": "Klasse-E.ipynb",
      "path": "Klasse-E.ipynb",
      "size": 3673469,
      "type": "notebook",
      "writable": true
    },
    {
      "content": null,
      "created": "2025-11-17T23:57:04.541901Z",
      "format": null,
      "hash": null,
      "hash_algorithm": null,
      "last_modified": "2025-11-17T23:57:01.401879Z",
      "mimetype": null,
      "name": "Filters.ipynb",
      "path": "Filters.ipynb",
      "size": 2293883,
      "type": "notebook",
      "writable": true
    },
    {
      "content": null,
      "created": "2025-11-17T23:57:04.614901Z",
      "format": null,
      "hash": null,
      "hash_algorithm": null,
      "last_modified": "2025-11-17T23:51:01.845313Z",
      "mimetype": "application/yaml",
      "name": "_toc.yml",
      "path": "_toc.yml",
      "size": 1079,
      "type": "file",
      "writable": true
    },
    {
      "content": null,
      "created": "2025-11-17T23:57:04.632901Z",
      "format": null,
      "hash": null,
      "hash_algorithm": null,
      "last_modified": "2025-11-17T23:57:04.632901Z",
      "mimetype": null,
      "name": "simul",
      "path": "simul",
      "size": null,
      "type": "directory",
      "writable": true
    },
    {
      "content": null,
      "created": "2025-11-17T23:57:04.606901Z",
      "format": null,
      "hash": null,
      "hash_algorithm": null,
      "last_modified": "2025-11-17T23:57:01.411879Z",
      "mimetype": null,
      "name": "SmithKaartOefening6.ipynb",
      "path": "SmithKaartOefening6.ipynb",
      "size": 663586,
      "type": "notebook",
      "writable": true
    }
  ],
  "created": "2025-11-17T23:57:04.634901Z",
  "format": "json",
  "hash": null,
  "hash_algorithm": null,
  "last_modified": "2025-11-17T23:57:04.634901Z",
  "mimetype": null,
  "name": "",
  "path": "",
  "size": null,
  "type": "directory",
  "writable": true
}