{
  "content": [
    {
      "content": null,
      "created": "2023-08-06T21:48:03.550551Z",
      "format": null,
      "last_modified": "2023-08-06T21:48:03.550551Z",
      "mimetype": null,
      "name": "images",
      "path": "./images",
      "size": null,
      "type": "directory",
      "writable": true
    },
    {
      "content": null,
      "created": "2023-08-06T21:48:03.530551Z",
      "format": null,
      "last_modified": "2023-08-06T21:47:13.801952Z",
      "mimetype": null,
      "name": "SmithKaartOefening5.ipynb",
      "path": "./SmithKaartOefening5.ipynb",
      "size": 2290859,
      "type": "notebook",
      "writable": true
    },
    {
      "content": null,
      "created": "2023-08-06T21:48:03.494551Z",
      "format": null,
      "last_modified": "2023-08-06T21:47:13.733952Z",
      "mimetype": null,
      "name": "Klasse-E.ipynb",
      "path": "./Klasse-E.ipynb",
      "size": 2772038,
      "type": "notebook",
      "writable": true
    },
    {
      "content": null,
      "created": "2023-08-06T21:48:03.558551Z",
      "format": null,
      "last_modified": "2023-08-06T21:47:13.821952Z",
      "mimetype": null,
      "name": "transmissielijn.ipynb",
      "path": "./transmissielijn.ipynb",
      "size": 260138,
      "type": "notebook",
      "writable": true
    },
    {
      "content": null,
      "created": "2023-08-06T21:48:03.502551Z",
      "format": null,
      "last_modified": "2023-08-06T21:47:13.741952Z",
      "mimetype": "text/markdown",
      "name": "References.md",
      "path": "./References.md",
      "size": 53,
      "type": "file",
      "writable": true
    },
    {
      "content": null,
      "created": "2023-08-06T21:48:03.558551Z",
      "format": null,
      "last_modified": "2023-08-06T21:48:03.558551Z",
      "mimetype": null,
      "name": "simul",
      "path": "./simul",
      "size": null,
      "type": "directory",
      "writable": true
    },
    {
      "content": null,
      "created": "2023-08-06T21:48:03.482551Z",
      "format": null,
      "last_modified": "2023-08-06T21:47:13.713952Z",
      "mimetype": null,
      "name": "Klasse-C.ipynb",
      "path": "./Klasse-C.ipynb",
      "size": 2901736,
      "type": "notebook",
      "writable": true
    },
    {
      "content": null,
      "created": "2023-08-06T21:48:03.542551Z",
      "format": null,
      "last_modified": "2023-08-06T21:47:13.813952Z",
      "mimetype": null,
      "name": "Spice-simulatie.ipynb",
      "path": "./Spice-simulatie.ipynb",
      "size": 406116,
      "type": "notebook",
      "writable": true
    },
    {
      "content": null,
      "created": "2023-08-06T21:48:03.538551Z",
      "format": null,
      "last_modified": "2023-08-06T21:47:13.805952Z",
      "mimetype": null,
      "name": "SmithKaartOefening6.ipynb",
      "path": "./SmithKaartOefening6.ipynb",
      "size": 662896,
      "type": "notebook",
      "writable": true
    },
    {
      "content": null,
      "created": "2023-08-06T21:48:03.538551Z",
      "format": null,
      "last_modified": "2023-08-06T21:47:13.809952Z",
      "mimetype": null,
      "name": "SmithKaartOefening8.ipynb",
      "path": "./SmithKaartOefening8.ipynb",
      "size": 188776,
      "type": "notebook",
      "writable": true
    },
    {
      "content": null,
      "created": "2023-08-06T21:48:03.542551Z",
      "format": null,
      "last_modified": "2023-08-06T21:47:13.813952Z",
      "mimetype": null,
      "name": "_tocpdf.yml",
      "path": "./_tocpdf.yml",
      "size": 654,
      "type": "file",
      "writable": true
    },
    {
      "content": null,
      "created": "2023-08-06T21:48:03.542551Z",
      "format": null,
      "last_modified": "2023-08-06T21:47:13.813952Z",
      "mimetype": null,
      "name": "_toc.yml",
      "path": "./_toc.yml",
      "size": 921,
      "type": "file",
      "writable": true
    },
    {
      "content": null,
      "created": "2023-08-06T21:48:03.518551Z",
      "format": null,
      "last_modified": "2023-08-06T21:47:13.773952Z",
      "mimetype": null,
      "name": "SmithKaartOefening3.ipynb",
      "path": "./SmithKaartOefening3.ipynb",
      "size": 2274341,
      "type": "notebook",
      "writable": true
    },
    {
      "content": null,
      "created": "2023-08-06T21:48:03.478551Z",
      "format": null,
      "last_modified": "2023-08-06T21:47:13.697952Z",
      "mimetype": null,
      "name": "Filters.ipynb",
      "path": "./Filters.ipynb",
      "size": 1294618,
      "type": "notebook",
      "writable": true
    },
    {
      "content": null,
      "created": "2023-08-06T21:48:03.542551Z",
      "format": null,
      "last_modified": "2023-08-06T21:47:13.813952Z",
      "mimetype": "text/x-bibtex",
      "name": "ToegepasteAnalogeElektronica.bib",
      "path": "./ToegepasteAnalogeElektronica.bib",
      "size": 537,
      "type": "file",
      "writable": true
    },
    {
      "content": null,
      "created": "2023-08-06T21:48:03.526551Z",
      "format": null,
      "last_modified": "2023-08-06T21:47:13.789952Z",
      "mimetype": null,
      "name": "SmithKaartOefening4.ipynb",
      "path": "./SmithKaartOefening4.ipynb",
      "size": 2297559,
      "type": "notebook",
      "writable": true
    },
    {
      "content": null,
      "created": "2023-08-06T21:48:03.538551Z",
      "format": null,
      "last_modified": "2023-08-06T21:47:13.809952Z",
      "mimetype": null,
      "name": "SmithKaartOefening7.ipynb",
      "path": "./SmithKaartOefening7.ipynb",
      "size": 493101,
      "type": "notebook",
      "writable": true
    },
    {
      "content": null,
      "created": "2023-08-06T21:48:03.510551Z",
      "format": null,
      "last_modified": "2023-08-06T21:47:13.757952Z",
      "mimetype": null,
      "name": "SmithKaartOefening2.ipynb",
      "path": "./SmithKaartOefening2.ipynb",
      "size": 2267725,
      "type": "notebook",
      "writable": true
    },
    {
      "content": null,
      "created": "2023-08-06T21:48:03.490551Z",
      "format": null,
      "last_modified": "2023-08-06T21:47:13.721952Z",
      "mimetype": null,
      "name": "Klasse-D.ipynb",
      "path": "./Klasse-D.ipynb",
      "size": 1333424,
      "type": "notebook",
      "writable": true
    },
    {
      "content": null,
      "created": "2023-08-06T21:48:03.542551Z",
      "format": null,
      "last_modified": "2023-08-06T21:48:01.698537Z",
      "mimetype": "text/x-python",
      "name": "cursusdef.py",
      "path": "./cursusdef.py",
      "size": 779,
      "type": "file",
      "writable": true
    },
    {
      "content": null,
      "created": "2023-08-06T21:48:03.506551Z",
      "format": null,
      "last_modified": "2023-08-06T21:47:13.745952Z",
      "mimetype": null,
      "name": "SmithKaart.ipynb",
      "path": "./SmithKaart.ipynb",
      "size": 1487338,
      "type": "notebook",
      "writable": true
    },
    {
      "content": null,
      "created": "2023-08-06T21:48:03.554551Z",
      "format": null,
      "last_modified": "2023-08-06T21:47:13.817952Z",
      "mimetype": "text/markdown",
      "name": "intro.md",
      "path": "./intro.md",
      "size": 973,
      "type": "file",
      "writable": true
    },
    {
      "content": null,
      "created": "2023-08-06T21:48:03.502551Z",
      "format": null,
      "last_modified": "2023-08-06T21:47:13.737952Z",
      "mimetype": null,
      "name": "Klasse-F.ipynb",
      "path": "./Klasse-F.ipynb",
      "size": 832706,
      "type": "notebook",
      "writable": true
    },
    {
      "content": null,
      "created": "2023-08-06T21:48:03.510551Z",
      "format": null,
      "last_modified": "2023-08-06T21:47:13.745952Z",
      "mimetype": null,
      "name": "SmithKaartOefening1.ipynb",
      "path": "./SmithKaartOefening1.ipynb",
      "size": 230990,
      "type": "notebook",
      "writable": true
    },
    {
      "content": null,
      "created": "2023-08-06T21:48:03.554551Z",
      "format": null,
      "last_modified": "2023-08-06T21:47:13.817952Z",
      "mimetype": "text/markdown",
      "name": "intro2.md",
      "path": "./intro2.md",
      "size": 579,
      "type": "file",
      "writable": true
    },
    {
      "content": null,
      "created": "2023-08-06T21:48:03.554551Z",
      "format": null,
      "last_modified": "2023-08-06T21:47:13.817952Z",
      "mimetype": null,
      "name": "reflecties.ipynb",
      "path": "./reflecties.ipynb",
      "size": 48528,
      "type": "notebook",
      "writable": true
    },
    {
      "content": null,
      "created": "2023-08-06T21:48:03.542551Z",
      "format": null,
      "last_modified": "2023-08-06T21:47:13.813952Z",
      "mimetype": null,
      "name": "_config.yml",
      "path": "./_config.yml",
      "size": 1807,
      "type": "file",
      "writable": true
    }
  ],
  "created": "2023-08-06T21:48:03.558551Z",
  "format": "json",
  "last_modified": "2023-08-06T21:48:03.558551Z",
  "mimetype": null,
  "name": ".",
  "path": ".",
  "size": null,
  "type": "directory",
  "writable": true
}