{
  "content": [
    {
      "content": null,
      "created": "2023-11-12T23:14:41.907370Z",
      "format": null,
      "last_modified": "2023-11-12T23:13:49.031549Z",
      "mimetype": null,
      "name": "transmissielijn.ipynb",
      "path": "transmissielijn.ipynb",
      "size": 259480,
      "type": "notebook",
      "writable": true
    },
    {
      "content": null,
      "created": "2023-11-12T23:14:41.823370Z",
      "format": null,
      "last_modified": "2023-11-12T23:13:48.895551Z",
      "mimetype": null,
      "name": "Klasse-C.ipynb",
      "path": "Klasse-C.ipynb",
      "size": 3025891,
      "type": "notebook",
      "writable": true
    },
    {
      "content": null,
      "created": "2023-11-12T23:14:41.835370Z",
      "format": null,
      "last_modified": "2023-11-12T23:13:48.927551Z",
      "mimetype": null,
      "name": "Klasse-E.ipynb",
      "path": "Klasse-E.ipynb",
      "size": 3040011,
      "type": "notebook",
      "writable": true
    },
    {
      "content": null,
      "created": "2023-11-12T23:14:41.891370Z",
      "format": null,
      "last_modified": "2023-11-12T23:14:39.823381Z",
      "mimetype": "text/x-python",
      "name": "cursusdef.py",
      "path": "cursusdef.py",
      "size": 779,
      "type": "file",
      "writable": true
    },
    {
      "content": null,
      "created": "2023-11-12T23:14:41.843370Z",
      "format": null,
      "last_modified": "2023-11-12T23:13:48.931551Z",
      "mimetype": null,
      "name": "Klasse-F.ipynb",
      "path": "Klasse-F.ipynb",
      "size": 847243,
      "type": "notebook",
      "writable": true
    },
    {
      "content": null,
      "created": "2023-11-12T23:14:41.831370Z",
      "format": null,
      "last_modified": "2023-11-12T23:13:48.907551Z",
      "mimetype": null,
      "name": "Klasse-D.ipynb",
      "path": "Klasse-D.ipynb",
      "size": 1544783,
      "type": "notebook",
      "writable": true
    },
    {
      "content": null,
      "created": "2023-11-12T23:14:41.851370Z",
      "format": null,
      "last_modified": "2023-11-12T23:13:48.943551Z",
      "mimetype": null,
      "name": "SmithKaartOefening1.ipynb",
      "path": "SmithKaartOefening1.ipynb",
      "size": 802858,
      "type": "notebook",
      "writable": true
    },
    {
      "content": null,
      "created": "2023-11-12T23:14:41.899370Z",
      "format": null,
      "last_modified": "2023-11-12T23:13:49.027550Z",
      "mimetype": "text/markdown",
      "name": "intro2.md",
      "path": "intro2.md",
      "size": 569,
      "type": "file",
      "writable": true
    },
    {
      "content": null,
      "created": "2023-11-12T23:14:41.847370Z",
      "format": null,
      "last_modified": "2023-11-12T23:13:48.935551Z",
      "mimetype": null,
      "name": "SmithKaart.ipynb",
      "path": "SmithKaart.ipynb",
      "size": 1486856,
      "type": "notebook",
      "writable": true
    },
    {
      "content": null,
      "created": "2023-11-12T23:14:41.891370Z",
      "format": null,
      "last_modified": "2023-11-12T23:13:49.019550Z",
      "mimetype": null,
      "name": "_tocpdf.yml",
      "path": "_tocpdf.yml",
      "size": 654,
      "type": "file",
      "writable": true
    },
    {
      "content": null,
      "created": "2023-11-12T23:14:41.891370Z",
      "format": null,
      "last_modified": "2023-11-12T23:13:49.019550Z",
      "mimetype": null,
      "name": "_config.yml",
      "path": "_config.yml",
      "size": 1794,
      "type": "file",
      "writable": true
    },
    {
      "content": null,
      "created": "2023-11-12T23:14:41.891370Z",
      "format": null,
      "last_modified": "2023-11-12T23:13:49.019550Z",
      "mimetype": "text/x-bibtex",
      "name": "ToegepasteAnalogeElektronica.bib",
      "path": "ToegepasteAnalogeElektronica.bib",
      "size": 6094,
      "type": "file",
      "writable": true
    },
    {
      "content": null,
      "created": "2023-11-12T23:14:41.815371Z",
      "format": null,
      "last_modified": "2023-11-12T23:13:48.879552Z",
      "mimetype": null,
      "name": "Filters.ipynb",
      "path": "Filters.ipynb",
      "size": 1335063,
      "type": "notebook",
      "writable": true
    },
    {
      "content": null,
      "created": "2023-11-12T23:14:41.847370Z",
      "format": null,
      "last_modified": "2023-11-12T23:13:48.931551Z",
      "mimetype": "text/markdown",
      "name": "References.md",
      "path": "References.md",
      "size": 53,
      "type": "file",
      "writable": true
    },
    {
      "content": null,
      "created": "2023-11-12T23:14:41.903370Z",
      "format": null,
      "last_modified": "2023-11-12T23:13:49.027550Z",
      "mimetype": null,
      "name": "reflecties.ipynb",
      "path": "reflecties.ipynb",
      "size": 47673,
      "type": "notebook",
      "writable": true
    },
    {
      "content": null,
      "created": "2023-11-12T23:14:41.907370Z",
      "format": null,
      "last_modified": "2023-11-12T23:14:41.907370Z",
      "mimetype": null,
      "name": "simul",
      "path": "simul",
      "size": null,
      "type": "directory",
      "writable": true
    },
    {
      "content": null,
      "created": "2023-11-12T23:14:41.899370Z",
      "format": null,
      "last_modified": "2023-11-12T23:14:41.899370Z",
      "mimetype": null,
      "name": "images",
      "path": "images",
      "size": null,
      "type": "directory",
      "writable": true
    },
    {
      "content": null,
      "created": "2023-11-12T23:14:41.855370Z",
      "format": null,
      "last_modified": "2023-11-12T23:13:48.959551Z",
      "mimetype": null,
      "name": "SmithKaartOefening2.ipynb",
      "path": "SmithKaartOefening2.ipynb",
      "size": 2271471,
      "type": "notebook",
      "writable": true
    },
    {
      "content": null,
      "created": "2023-11-12T23:14:41.887370Z",
      "format": null,
      "last_modified": "2023-11-12T23:13:49.019550Z",
      "mimetype": null,
      "name": "SmithKaartOefening8.ipynb",
      "path": "SmithKaartOefening8.ipynb",
      "size": 752584,
      "type": "notebook",
      "writable": true
    },
    {
      "content": null,
      "created": "2023-11-12T23:14:41.863370Z",
      "format": null,
      "last_modified": "2023-11-12T23:13:48.971550Z",
      "mimetype": null,
      "name": "SmithKaartOefening3.ipynb",
      "path": "SmithKaartOefening3.ipynb",
      "size": 2273194,
      "type": "notebook",
      "writable": true
    },
    {
      "content": null,
      "created": "2023-11-12T23:14:41.883370Z",
      "format": null,
      "last_modified": "2023-11-12T23:13:49.011550Z",
      "mimetype": null,
      "name": "SmithKaartOefening6.ipynb",
      "path": "SmithKaartOefening6.ipynb",
      "size": 661902,
      "type": "notebook",
      "writable": true
    },
    {
      "content": null,
      "created": "2023-11-12T23:14:41.879370Z",
      "format": null,
      "last_modified": "2023-11-12T23:13:49.003550Z",
      "mimetype": null,
      "name": "SmithKaartOefening5.ipynb",
      "path": "SmithKaartOefening5.ipynb",
      "size": 2349348,
      "type": "notebook",
      "writable": true
    },
    {
      "content": null,
      "created": "2023-11-12T23:14:41.887370Z",
      "format": null,
      "last_modified": "2023-11-12T23:13:49.015550Z",
      "mimetype": null,
      "name": "SmithKaartOefening7.ipynb",
      "path": "SmithKaartOefening7.ipynb",
      "size": 503476,
      "type": "notebook",
      "writable": true
    },
    {
      "content": null,
      "created": "2023-11-12T23:14:41.871370Z",
      "format": null,
      "last_modified": "2023-11-12T23:13:48.987550Z",
      "mimetype": null,
      "name": "SmithKaartOefening4.ipynb",
      "path": "SmithKaartOefening4.ipynb",
      "size": 2296647,
      "type": "notebook",
      "writable": true
    },
    {
      "content": null,
      "created": "2023-11-12T23:14:41.891370Z",
      "format": null,
      "last_modified": "2023-11-12T23:13:49.019550Z",
      "mimetype": null,
      "name": "Spice-simulatie.ipynb",
      "path": "Spice-simulatie.ipynb",
      "size": 412545,
      "type": "notebook",
      "writable": true
    },
    {
      "content": null,
      "created": "2023-11-12T23:14:41.899370Z",
      "format": null,
      "last_modified": "2023-11-12T23:13:49.027550Z",
      "mimetype": "text/markdown",
      "name": "intro.md",
      "path": "intro.md",
      "size": 963,
      "type": "file",
      "writable": true
    },
    {
      "content": null,
      "created": "2023-11-12T23:14:41.891370Z",
      "format": null,
      "last_modified": "2023-11-12T23:13:49.019550Z",
      "mimetype": null,
      "name": "_toc.yml",
      "path": "_toc.yml",
      "size": 921,
      "type": "file",
      "writable": true
    }
  ],
  "created": "2023-11-12T23:14:41.907370Z",
  "format": "json",
  "last_modified": "2023-11-12T23:14:41.907370Z",
  "mimetype": null,
  "name": "",
  "path": "",
  "size": null,
  "type": "directory",
  "writable": true
}