{
  "content": [
    {
      "content": null,
      "created": "2024-12-26T23:20:42.552949Z",
      "format": null,
      "hash": null,
      "hash_algorithm": null,
      "last_modified": "2024-12-26T23:13:44.391891Z",
      "mimetype": "application/yaml",
      "name": "_tocpdf.yml",
      "path": "_tocpdf.yml",
      "size": 620,
      "type": "file",
      "writable": true
    },
    {
      "content": null,
      "created": "2024-12-26T23:20:42.563949Z",
      "format": null,
      "hash": null,
      "hash_algorithm": null,
      "last_modified": "2024-12-26T23:20:42.563949Z",
      "mimetype": null,
      "name": "libraries",
      "path": "libraries",
      "size": null,
      "type": "directory",
      "writable": true
    },
    {
      "content": null,
      "created": "2024-12-26T23:20:42.545949Z",
      "format": null,
      "hash": null,
      "hash_algorithm": null,
      "last_modified": "2024-12-26T23:20:38.664973Z",
      "mimetype": null,
      "name": "KlasseB_vb1.ipynb",
      "path": "KlasseB_vb1.ipynb",
      "size": 1053653,
      "type": "notebook",
      "writable": true
    },
    {
      "content": null,
      "created": "2024-12-26T23:20:42.525949Z",
      "format": null,
      "hash": null,
      "hash_algorithm": null,
      "last_modified": "2024-12-26T23:20:38.670974Z",
      "mimetype": null,
      "name": "Buck-converter.ipynb",
      "path": "Buck-converter.ipynb",
      "size": 407768,
      "type": "notebook",
      "writable": true
    },
    {
      "content": null,
      "created": "2024-12-26T23:20:42.543949Z",
      "format": null,
      "hash": null,
      "hash_algorithm": null,
      "last_modified": "2024-12-26T23:20:38.678973Z",
      "mimetype": null,
      "name": "Klasse-G.ipynb",
      "path": "Klasse-G.ipynb",
      "size": 404602,
      "type": "notebook",
      "writable": true
    },
    {
      "content": null,
      "created": "2024-12-26T23:20:42.529949Z",
      "format": null,
      "hash": null,
      "hash_algorithm": null,
      "last_modified": "2024-12-26T23:20:38.682973Z",
      "mimetype": null,
      "name": "Klasse-B-vb4.ipynb",
      "path": "Klasse-B-vb4.ipynb",
      "size": 177801,
      "type": "notebook",
      "writable": true
    },
    {
      "content": null,
      "created": "2024-12-26T23:20:42.566949Z",
      "format": null,
      "hash": null,
      "hash_algorithm": null,
      "last_modified": "2024-12-26T23:20:38.686973Z",
      "mimetype": null,
      "name": "oefeningBoost3.ipynb",
      "path": "oefeningBoost3.ipynb",
      "size": 153150,
      "type": "notebook",
      "writable": true
    },
    {
      "content": null,
      "created": "2024-12-26T23:20:42.524949Z",
      "format": null,
      "hash": null,
      "hash_algorithm": null,
      "last_modified": "2024-12-26T23:20:38.687973Z",
      "mimetype": null,
      "name": "Boost-converter.ipynb",
      "path": "Boost-converter.ipynb",
      "size": 44480,
      "type": "notebook",
      "writable": true
    },
    {
      "content": null,
      "created": "2024-12-26T23:20:42.560949Z",
      "format": null,
      "hash": null,
      "hash_algorithm": null,
      "last_modified": "2024-12-26T23:13:44.398891Z",
      "mimetype": "text/markdown",
      "name": "intro.md",
      "path": "intro.md",
      "size": 659,
      "type": "file",
      "writable": true
    },
    {
      "content": null,
      "created": "2024-12-26T23:20:42.560949Z",
      "format": null,
      "hash": null,
      "hash_algorithm": null,
      "last_modified": "2024-12-26T23:20:42.560949Z",
      "mimetype": null,
      "name": "images",
      "path": "images",
      "size": null,
      "type": "directory",
      "writable": true
    },
    {
      "content": null,
      "created": "2024-12-26T23:20:42.570949Z",
      "format": null,
      "hash": null,
      "hash_algorithm": null,
      "last_modified": "2024-12-26T23:20:42.570949Z",
      "mimetype": null,
      "name": "simul",
      "path": "simul",
      "size": null,
      "type": "directory",
      "writable": true
    },
    {
      "content": null,
      "created": "2024-12-26T23:20:42.565949Z",
      "format": null,
      "hash": null,
      "hash_algorithm": null,
      "last_modified": "2024-12-26T23:20:38.693973Z",
      "mimetype": null,
      "name": "oefeningBoost1.ipynb",
      "path": "oefeningBoost1.ipynb",
      "size": 115644,
      "type": "notebook",
      "writable": true
    },
    {
      "content": null,
      "created": "2024-12-26T23:20:42.549949Z",
      "format": null,
      "hash": null,
      "hash_algorithm": null,
      "last_modified": "2024-12-26T23:13:44.388891Z",
      "mimetype": "text/markdown",
      "name": "References.md",
      "path": "References.md",
      "size": 53,
      "type": "file",
      "writable": true
    },
    {
      "content": null,
      "created": "2024-12-26T23:20:42.548949Z",
      "format": null,
      "hash": null,
      "hash_algorithm": null,
      "last_modified": "2024-12-26T23:20:38.697973Z",
      "mimetype": null,
      "name": "KlasseB_vb3.ipynb",
      "path": "KlasseB_vb3.ipynb",
      "size": 327622,
      "type": "notebook",
      "writable": true
    },
    {
      "content": null,
      "created": "2024-12-26T23:20:42.549949Z",
      "format": null,
      "hash": null,
      "hash_algorithm": null,
      "last_modified": "2024-12-26T23:20:38.715973Z",
      "mimetype": null,
      "name": "TransistorConfiguraties.ipynb",
      "path": "TransistorConfiguraties.ipynb",
      "size": 801133,
      "type": "notebook",
      "writable": true
    },
    {
      "content": null,
      "created": "2024-12-26T23:20:42.526949Z",
      "format": null,
      "hash": null,
      "hash_algorithm": null,
      "last_modified": "2024-12-26T23:20:38.717973Z",
      "mimetype": null,
      "name": "Flyback-converter.ipynb",
      "path": "Flyback-converter.ipynb",
      "size": 27601,
      "type": "notebook",
      "writable": true
    },
    {
      "content": null,
      "created": "2024-12-26T23:20:42.551949Z",
      "format": null,
      "hash": null,
      "hash_algorithm": null,
      "last_modified": "2024-12-26T23:13:44.391891Z",
      "mimetype": "application/yaml",
      "name": "_toc.yml",
      "path": "_toc.yml",
      "size": 869,
      "type": "file",
      "writable": true
    },
    {
      "content": null,
      "created": "2024-12-26T23:20:42.551949Z",
      "format": null,
      "hash": null,
      "hash_algorithm": null,
      "last_modified": "2024-12-26T23:13:44.391891Z",
      "mimetype": "application/yaml",
      "name": "_config.yml",
      "path": "_config.yml",
      "size": 2334,
      "type": "file",
      "writable": true
    },
    {
      "content": null,
      "created": "2024-12-26T23:20:42.526949Z",
      "format": null,
      "hash": null,
      "hash_algorithm": null,
      "last_modified": "2024-12-26T23:20:38.718973Z",
      "mimetype": null,
      "name": "Inverter.ipynb",
      "path": "Inverter.ipynb",
      "size": 17058,
      "type": "notebook",
      "writable": true
    },
    {
      "content": null,
      "created": "2024-12-26T23:20:42.547949Z",
      "format": null,
      "hash": null,
      "hash_algorithm": null,
      "last_modified": "2024-12-26T23:20:38.722973Z",
      "mimetype": null,
      "name": "KlasseB_vb2.ipynb",
      "path": "KlasseB_vb2.ipynb",
      "size": 236827,
      "type": "notebook",
      "writable": true
    },
    {
      "content": null,
      "created": "2024-12-26T23:20:42.527949Z",
      "format": null,
      "hash": null,
      "hash_algorithm": null,
      "last_modified": "2024-12-26T23:20:38.735973Z",
      "mimetype": null,
      "name": "Klasse-A.ipynb",
      "path": "Klasse-A.ipynb",
      "size": 735304,
      "type": "notebook",
      "writable": true
    },
    {
      "content": null,
      "created": "2024-12-26T23:20:42.533949Z",
      "format": null,
      "hash": null,
      "hash_algorithm": null,
      "last_modified": "2024-12-26T23:20:38.861972Z",
      "mimetype": null,
      "name": "Klasse-B.ipynb",
      "path": "Klasse-B.ipynb",
      "size": 5425939,
      "type": "notebook",
      "writable": true
    },
    {
      "content": null,
      "created": "2024-12-26T23:20:42.561949Z",
      "format": null,
      "hash": null,
      "hash_algorithm": null,
      "last_modified": "2024-12-26T23:13:44.398891Z",
      "mimetype": "text/markdown",
      "name": "intro2.md",
      "path": "intro2.md",
      "size": 598,
      "type": "file",
      "writable": true
    },
    {
      "content": null,
      "created": "2024-12-26T23:20:42.553949Z",
      "format": null,
      "hash": null,
      "hash_algorithm": null,
      "last_modified": "2024-12-26T23:20:38.866972Z",
      "mimetype": null,
      "name": "buck.ipynb",
      "path": "buck.ipynb",
      "size": 143156,
      "type": "notebook",
      "writable": true
    },
    {
      "content": null,
      "created": "2024-12-26T23:20:42.554949Z",
      "format": null,
      "hash": null,
      "hash_algorithm": null,
      "last_modified": "2024-12-26T23:20:30.383027Z",
      "mimetype": "text/x-python",
      "name": "cursusdef.py",
      "path": "cursusdef.py",
      "size": 779,
      "type": "file",
      "writable": true
    },
    {
      "content": null,
      "created": "2024-12-26T23:20:42.524949Z",
      "format": null,
      "hash": null,
      "hash_algorithm": null,
      "last_modified": "2024-12-26T23:13:44.353891Z",
      "mimetype": "text/x-bibtex",
      "name": "AnalogeElektronica2.bib",
      "path": "AnalogeElektronica2.bib",
      "size": 2504,
      "type": "file",
      "writable": true
    },
    {
      "content": null,
      "created": "2024-12-26T23:20:42.553949Z",
      "format": null,
      "hash": null,
      "hash_algorithm": null,
      "last_modified": "2024-12-26T23:20:38.868972Z",
      "mimetype": null,
      "name": "buck_pfm.ipynb",
      "path": "buck_pfm.ipynb",
      "size": 54957,
      "type": "notebook",
      "writable": true
    },
    {
      "content": null,
      "created": "2024-12-26T23:20:42.566949Z",
      "format": null,
      "hash": null,
      "hash_algorithm": null,
      "last_modified": "2024-12-26T23:20:38.869972Z",
      "mimetype": null,
      "name": "oefeningBoost2.ipynb",
      "path": "oefeningBoost2.ipynb",
      "size": 3249,
      "type": "notebook",
      "writable": true
    },
    {
      "content": null,
      "created": "2024-12-26T23:20:42.552949Z",
      "format": null,
      "hash": null,
      "hash_algorithm": null,
      "last_modified": "2024-12-26T23:20:38.880972Z",
      "mimetype": null,
      "name": "berekening.ipynb",
      "path": "berekening.ipynb",
      "size": 191540,
      "type": "notebook",
      "writable": true
    }
  ],
  "created": "2024-12-26T23:20:42.566949Z",
  "format": "json",
  "hash": null,
  "hash_algorithm": null,
  "last_modified": "2024-12-26T23:20:42.566949Z",
  "mimetype": null,
  "name": "",
  "path": "",
  "size": null,
  "type": "directory",
  "writable": true
}