{
  "content": [
    {
      "content": null,
      "created": "2025-10-08T21:29:23.625286Z",
      "format": null,
      "hash": null,
      "hash_algorithm": null,
      "last_modified": "2025-10-08T21:21:47.345536Z",
      "mimetype": null,
      "name": "1N4148.lib",
      "path": "libraries/diode/switching/1N4148.lib",
      "size": 773,
      "type": "file",
      "writable": true
    }
  ],
  "created": "2025-10-08T21:29:23.625286Z",
  "format": "json",
  "hash": null,
  "hash_algorithm": null,
  "last_modified": "2025-10-08T21:29:23.625286Z",
  "mimetype": null,
  "name": "switching",
  "path": "libraries/diode/switching",
  "size": null,
  "type": "directory",
  "writable": true
}