{
  "content": [
    {
      "content": null,
      "created": "2024-01-08T16:44:08.931731Z",
      "format": null,
      "hash": null,
      "hash_algorithm": null,
      "last_modified": "2024-01-08T16:38:34.935278Z",
      "mimetype": null,
      "name": "BAV21.lib",
      "path": "libraries/diode/general-purpose/BAV21.lib",
      "size": 612,
      "type": "file",
      "writable": true
    }
  ],
  "created": "2024-01-08T16:44:08.931731Z",
  "format": "json",
  "hash": null,
  "hash_algorithm": null,
  "last_modified": "2024-01-08T16:44:08.931731Z",
  "mimetype": null,
  "name": "general-purpose",
  "path": "libraries/diode/general-purpose",
  "size": null,
  "type": "directory",
  "writable": true
}