{
  "content": [
    {
      "content": null,
      "created": "2024-07-02T20:00:31.188682Z",
      "format": null,
      "hash": null,
      "hash_algorithm": null,
      "last_modified": "2024-07-02T19:55:16.443318Z",
      "mimetype": null,
      "name": "1N5919B.lib",
      "path": "libraries/diode/zener/1N5919B.lib",
      "size": 1210,
      "type": "file",
      "writable": true
    }
  ],
  "created": "2024-07-02T20:00:31.188682Z",
  "format": "json",
  "hash": null,
  "hash_algorithm": null,
  "last_modified": "2024-07-02T20:00:31.188682Z",
  "mimetype": null,
  "name": "zener",
  "path": "libraries/diode/zener",
  "size": null,
  "type": "directory",
  "writable": true
}