{
  "content": [
    {
      "content": null,
      "created": "2026-02-16T19:37:57.315320Z",
      "format": null,
      "hash": null,
      "hash_algorithm": null,
      "last_modified": "2026-02-16T19:31:07.625375Z",
      "mimetype": "image/jpeg",
      "name": "image15.jpeg",
      "path": "images/KlasseA/image15.jpeg",
      "size": 128330,
      "type": "file",
      "writable": true
    }
  ],
  "created": "2026-02-16T19:37:57.315320Z",
  "format": "json",
  "hash": null,
  "hash_algorithm": null,
  "last_modified": "2026-02-16T19:37:57.315320Z",
  "mimetype": null,
  "name": "KlasseA",
  "path": "images/KlasseA",
  "size": null,
  "type": "directory",
  "writable": true
}